examples/__init__.py
examples/vsss_gym_basic.py
examples/vsss_gym_custom_obs_reward.py
examples/vsss_pettingzoo_basic.py
examples/vsss_simple_basic.py
examples/vsss_simple_hmi_basic.py
pSim/__init__.py
pSim/vsss_base_env.py
pSim/vsss_gym_env.py
pSim/vsss_pettingzoo_env.py
pSim/vsss_simple_env.py
pSim/config/game_config.json
pSim/modules/OUNoise.py
pSim/modules/__init__.py
pSim/modules/env_description.py
pSim/modules/game_setup.py
pSim/modules/hmi.py
pSim/modules/render_vsss.py
pSim/modules/simulator.py
pSim/pybox2d/__init__.py
pSim/pybox2d/setup.py
pSim/pybox2d/Box2D/Box2D.h
pSim/pybox2d/Box2D/Box2D_wrap.cpp
pSim/pybox2d/Box2D/Box2D_wrap.h
pSim/pybox2d/Box2D/Collision/b2BroadPhase.cpp
pSim/pybox2d/Box2D/Collision/b2BroadPhase.h
pSim/pybox2d/Box2D/Collision/b2CollideCircle.cpp
pSim/pybox2d/Box2D/Collision/b2CollideEdge.cpp
pSim/pybox2d/Box2D/Collision/b2CollidePolygon.cpp
pSim/pybox2d/Box2D/Collision/b2Collision.cpp
pSim/pybox2d/Box2D/Collision/b2Collision.h
pSim/pybox2d/Box2D/Collision/b2Distance.cpp
pSim/pybox2d/Box2D/Collision/b2Distance.h
pSim/pybox2d/Box2D/Collision/b2DynamicTree.cpp
pSim/pybox2d/Box2D/Collision/b2DynamicTree.h
pSim/pybox2d/Box2D/Collision/b2TimeOfImpact.cpp
pSim/pybox2d/Box2D/Collision/b2TimeOfImpact.h
pSim/pybox2d/Box2D/Collision/Shapes/b2ChainShape.cpp
pSim/pybox2d/Box2D/Collision/Shapes/b2ChainShape.h
pSim/pybox2d/Box2D/Collision/Shapes/b2CircleShape.cpp
pSim/pybox2d/Box2D/Collision/Shapes/b2CircleShape.h
pSim/pybox2d/Box2D/Collision/Shapes/b2EdgeShape.cpp
pSim/pybox2d/Box2D/Collision/Shapes/b2EdgeShape.h
pSim/pybox2d/Box2D/Collision/Shapes/b2PolygonShape.cpp
pSim/pybox2d/Box2D/Collision/Shapes/b2PolygonShape.h
pSim/pybox2d/Box2D/Collision/Shapes/b2Shape.h
pSim/pybox2d/Box2D/Common/b2BlockAllocator.cpp
pSim/pybox2d/Box2D/Common/b2BlockAllocator.h
pSim/pybox2d/Box2D/Common/b2Draw.cpp
pSim/pybox2d/Box2D/Common/b2Draw.h
pSim/pybox2d/Box2D/Common/b2GrowableStack.h
pSim/pybox2d/Box2D/Common/b2Math.cpp
pSim/pybox2d/Box2D/Common/b2Math.h
psim-0.2.4.dist-info/LICENSE
psim-0.2.4.dist-info/METADATA
psim-0.2.4.dist-info/WHEEL
psim-0.2.4.dist-info/entry_points.txt
psim-0.2.4.dist-info/top_level.txt
psim-0.2.4.dist-info/RECORD
