Metadata-Version: 2.2
Name: pSim
Version: 0.2.4
Summary: A pythonic Very Small Size Soccer (VSSS) simulation environment for reinforcement learning research.
Author-email: juliodltv <juliodltv@gmail.com>
License:                     GNU GENERAL PUBLIC LICENSE
Classifier: Development Status :: 3 - Alpha
Classifier: Intended Audience :: Developers
Classifier: Intended Audience :: Science/Research
Classifier: License :: OSI Approved :: GNU General Public License v3 (GPLv3)
Classifier: Programming Language :: Python :: 3
Classifier: Programming Language :: Python :: 3.12
Classifier: Operating System :: OS Independent
Classifier: Topic :: Scientific/Engineering :: Artificial Intelligence
Classifier: Topic :: Software Development :: Libraries :: Python Modules
Requires-Python: <3.12,>=3.11
License-File: LICENSE
Requires-Dist: pygame
Requires-Dist: scipy
Provides-Extra: gym
Requires-Dist: gymnasium; extra == "gym"
Provides-Extra: zoo
Requires-Dist: pettingzoo>=1.25.0; extra == "zoo"
Provides-Extra: docs
Requires-Dist: mkdocs-material; extra == "docs"
Requires-Dist: mkdocstrings[python]; extra == "docs"
Provides-Extra: tools
Requires-Dist: ruff; extra == "tools"
Requires-Dist: build; extra == "tools"
Provides-Extra: all
Requires-Dist: gymnasium; extra == "all"
Requires-Dist: pettingzoo>=1.25.0; extra == "all"
